neural_style/__init__.py
neural_style/neural_style.py
neural_style/loader/CaffeLoader.py
neural_style/loader/__init__.py
neural_style-0.5.7.dist-info/LICENSE
neural_style-0.5.7.dist-info/METADATA
neural_style-0.5.7.dist-info/WHEEL
neural_style-0.5.7.dist-info/entry_points.txt
neural_style-0.5.7.dist-info/top_level.txt
neural_style-0.5.7.dist-info/RECORD
