Metadata-Version: 2.1
Name: neural-style
Version: 0.5.7
Summary: A PyTorch implementation of artistic style transfer
Home-page: https://github.com/ProGamerGov/neural-style-pt/tree/pip-master/
Author: ProGamerGov
License: UNKNOWN
Keywords: neural artistic style neural-style neural-style-pt pytorch style transfer style-transfer pytorch-style-transfer neuralart neural-art nst neural-style-transfer deepstyle deep-style mlart machine-learning-art aiart ai-art gatys justin-johnson torch deepdream
Platform: UNKNOWN
Classifier: Development Status :: 5 - Production/Stable
Classifier: Intended Audience :: Science/Research
Classifier: Intended Audience :: End Users/Desktop
Classifier: Topic :: Artistic Software
Classifier: Topic :: Scientific/Engineering :: Artificial Intelligence
Classifier: Programming Language :: Python :: 2
Classifier: Programming Language :: Python :: 3
Classifier: License :: OSI Approved :: MIT License
Classifier: Operating System :: OS Independent
